pywharf_backends/github/__init__.py
pywharf_backends/github/impl.py
pywharf_github-0.2.0.dist-info/entry_points.txt
pywharf_github-0.2.0.dist-info/LICENSE
pywharf_github-0.2.0.dist-info/WHEEL
pywharf_github-0.2.0.dist-info/METADATA
pywharf_github-0.2.0.dist-info/RECORD
